LICENSE
MANIFEST.in
README.md
setup.py
OASYS1_shadow4_advanced.egg-info/PKG-INFO
OASYS1_shadow4_advanced.egg-info/SOURCES.txt
OASYS1_shadow4_advanced.egg-info/dependency_links.txt
OASYS1_shadow4_advanced.egg-info/entry_points.txt
OASYS1_shadow4_advanced.egg-info/namespace_packages.txt
OASYS1_shadow4_advanced.egg-info/not-zip-safe
OASYS1_shadow4_advanced.egg-info/requires.txt
OASYS1_shadow4_advanced.egg-info/top_level.txt
orangecontrib/__init__.py
orangecontrib/shadow4_advanced/__init__.py
orangecontrib/shadow4_advanced/widgets/__init__.py
orangecontrib/shadow4_advanced/widgets/tools/__init__.py
orangecontrib/shadow4_advanced/widgets/tools/ow_fixed_rods_bender_mirror.py
orangecontrib/shadow4_advanced/widgets/tools/ow_flexural_hinge_bender_mirror.py
orangecontrib/shadow4_advanced/widgets/tools/ow_hybrid_screen.py
orangecontrib/shadow4_advanced/widgets/tools/icons/advanced.png
orangecontrib/shadow4_advanced/widgets/tools/icons/fixed_rods_bender_mirror.png
orangecontrib/shadow4_advanced/widgets/tools/icons/fixed_rods_bender_scheme.png
orangecontrib/shadow4_advanced/widgets/tools/icons/flexural_hinge_bender_mirror.png
orangecontrib/shadow4_advanced/widgets/tools/icons/flexural_hinge_bender_scheme.png
orangecontrib/shadow4_advanced/widgets/tools/icons/hybrid_screen.png
orangecontrib/shadow4_advanced/widgets/tools/icons/zone_plate.png