Metadata-Version: 2.1
Name: OASYS1-shadow4-advanced
Version: 0.0.17
Summary: oasys-shadow4-advanced: Oasys widgets for shadow4 - advanced tools
Home-page: https://github.com/oasys-kit/OASYS1-SHADOW4-Advanced
Download-URL: https://github.com/oasys-kit/OASYS1-SHADOW4-Advanced
Author: M. Sanchez del Rio, L. Rebuffi
Author-email: lrebuffi@anl.gov
License: MIT
Keywords: ray tracing,x-ray optics,Oasys1
Classifier: Development Status :: 4 - Beta
Classifier: Environment :: X11 Applications :: Qt
Classifier: Environment :: Console
Classifier: Environment :: Plugins
Classifier: Programming Language :: Python
Classifier: Programming Language :: Python :: 3
Classifier: Intended Audience :: Science/Research
License-File: LICENSE
Requires-Dist: oasys1>=1.2.140
Requires-Dist: shadow4>=0.1.54
Requires-Dist: shadow4-advanced>=0.0.13
Requires-Dist: oasys1-shadow4>=0.0.70
